sortepack/__init__.py
sortepack/sorteios.py
sortepack-0.0.1.dist-info/METADATA
sortepack-0.0.1.dist-info/WHEEL
sortepack-0.0.1.dist-info/top_level.txt
sortepack-0.0.1.dist-info/RECORD
