Metadata-Version: 2.4
Name: sortepack
Version: 0.0.1
Summary: Pacote para sortear números e itens aleatórios.
Home-page: https://github.com/andissaura/simple-package-template
Author: Andi
Author-email: andissaura@gmail.com
Requires-Python: >=3.8
Dynamic: author
Dynamic: author-email
Dynamic: description
Dynamic: description-content-type
Dynamic: home-page
Dynamic: requires-python
Dynamic: summary
